cpymad/__init__.py
cpymad/_rpc.py
cpymad/clibmadx.pxd
cpymad/libmadx.c
cpymad/libmadx.cpython-310-aarch64-linux-gnu.so
cpymad/libmadx.pyx
cpymad/madx.py
cpymad/parsing.py
cpymad/stream.py
cpymad/types.py
cpymad/util.py
cpymad/COPYING/__init__.py
cpymad/COPYING/cpymad.rst
cpymad/COPYING/madx.rst
cpymad.libs/libgfortran-daac5196.so.5.0.0
cpymad-1.19.0.dist-info/METADATA
cpymad-1.19.0.dist-info/WHEEL
cpymad-1.19.0.dist-info/top_level.txt
cpymad-1.19.0.dist-info/RECORD
cpymad-1.19.0.dist-info/licenses/COPYING.rst
cpymad-1.19.0.dist-info/licenses/LICENSE/Apache
cpymad-1.19.0.dist-info/licenses/LICENSE/GPLv3
cpymad-1.19.0.dist-info/sboms/auditwheel.cdx.json
