Metadata-Version: 2.4
Name: cpymad
Version: 1.19.0
Summary: Cython binding to MAD-X
Author: Yngve Inntjore Levinsen, Kajetan Fuchsberger
Author-email: Thomas Gläßle <t_glaessle@gmx.de>
Maintainer-email: Thomas Gläßle <t_glaessle@gmx.de>, Riccardo De Maria <riccardodemaria@gmail.com>
License-Expression: GPL-3.0-or-later AND Apache-2.0 AND LicenseRef-CERN-MADX-Proprietary
Project-URL: Github, https://github.com/hibtc/cpymad
Project-URL: Issues, https://github.com/hibtc/cpymad/issues
Project-URL: Documentation, http://hibtc.github.io/cpymad/
Project-URL: Changelog, https://github.com/hibtc/cpymad/blob/master/CHANGES.rst
Classifier: Development Status :: 4 - Beta
Classifier: Intended Audience :: Science/Research
Classifier: Operating System :: MacOS :: MacOS X
Classifier: Operating System :: Microsoft :: Windows
Classifier: Operating System :: POSIX :: Linux
Classifier: Programming Language :: Python :: 3
Classifier: Topic :: Scientific/Engineering :: Physics
Requires-Python: >=3.10
License-File: COPYING.rst
License-File: LICENSE/Apache
License-File: LICENSE/GPLv3
Requires-Dist: numpy
Requires-Dist: minrpc>=0.1.0
Provides-Extra: doc
Requires-Dist: sphinx<9; extra == "doc"
Requires-Dist: sphinx_rtd_theme>=3; extra == "doc"
Requires-Dist: sphinx_substitution_extensions; extra == "doc"
Requires-Dist: sphinx_automodapi; extra == "doc"
Requires-Dist: sphinx_autodoc_typehints; extra == "doc"
Requires-Dist: pandas; extra == "doc"
Provides-Extra: dev
Requires-Dist: cython; extra == "dev"
Requires-Dist: ruff; extra == "dev"
Requires-Dist: pytest; extra == "dev"
Dynamic: license-file
